pyball/__init__.py
pyball/ball.py
pyball/base.py
pyball/core/__init__.py
pyball/core/endpoint_manager.py
pyball/core/requester.py
pyball/fundamentals/__init__.py
pyball/fundamentals/base_fundamental.py
pyball/fundamentals/competition_news.py
pyball/fundamentals/competition_stats.py
pyball/fundamentals/fixtures_all.py
pyball/fundamentals/news.py
pyball/fundamentals/team_top_scorers.py
pyball/modules/__init__.py
pyball/modules/all.py
pyball/modules/base_module.py
pyball/modules/competition.py
pyball/modules/team.py
pyball-0.1.0.dist-info/DESCRIPTION.rst
pyball-0.1.0.dist-info/METADATA
pyball-0.1.0.dist-info/RECORD
pyball-0.1.0.dist-info/WHEEL
pyball-0.1.0.dist-info/metadata.json
pyball-0.1.0.dist-info/top_level.txt
