Metadata-Version: 2.0
Name: pyball
Version: 0.1.0
Summary: A python client to get football news
Home-page: https://github.com/slapbot/newsapi
Author: Ujjwal Gupta
Author-email: ugupta41@gmail.com
License: MIT
Requires-Dist: requests
